jintegral/__init__.py
jintegral/abaqus_sample.py
jintegral/crack.py
jintegral/davis_sample.py
jintegral/fig_template.py
jintegral/frame.py
jintegral/jintegral.py
jintegral/material.py
jintegral/sample.py
jintegral/utils.py
jintegral/vic_sample.py
jintegral-1.0.1.dist-info/LICENSE
jintegral-1.0.1.dist-info/METADATA
jintegral-1.0.1.dist-info/WHEEL
jintegral-1.0.1.dist-info/RECORD
