Metadata-Version: 2.1
Name: jintegral
Version: 1.0.1
Summary: A Python implementation of J-integral data reduction for translaminar toughness of compact tension specimens
License: BSD3
Author: Guillaume Broggi
Author-email: 25569517+GuillaumeBroggi@users.noreply.github.com
Requires-Python: >=3.10,<3.12
Classifier: License :: Other/Proprietary License
Classifier: Programming Language :: Python :: 3
Classifier: Programming Language :: Python :: 3.10
Classifier: Programming Language :: Python :: 3.11
Requires-Dist: csaps (>=1.1.0,<2.0.0)
Requires-Dist: numpy (>=1.24.2,<2.0.0)
Requires-Dist: pandas (>=1.5.3,<2.0.0)
Requires-Dist: plotly (>=5.13.1,<6.0.0)
Requires-Dist: scikit-learn (>=1.2.1,<2.0.0)
Requires-Dist: scipy (>=1.10.1,<2.0.0)
Requires-Dist: tqdm (>=4.64.1,<5.0.0)
